Workbook

Sheet Dashboard
A1: SALES PERFORMANCE DASHBOARD
A2: Practice project using sample data | Excel formulas and charts
A4: Metric | B4: Value
A5: Total Sales | B5: =SUM('Sales Data'!H2:H121) -> 25266
A6: Total Profit | B6: =SUM('Sales Data'!J2:J121) -> 10690
A7: Total Orders | B7: =COUNTA('Sales Data'!A2:A121) -> 120
A8: Units Sold | B8: =SUM('Sales Data'!F2:F121) -> 812
A9: Profit Margin | B9: =IFERROR(B6/B5,0) -> 0.42309823
A12: Monthly Performance | E12: Sales by Category
A13: Month | B13: Sales | C13: Profit | E13: Category | F13: Sales
A14: 45658 | B14: =SUMIFS('Sales Data'!$H$2:$H$121,'Sales Data'!$B$2:$B$121,">="&A14,'Sales Data'!$B$2:$B$121,"<"&EDATE(A14,1)) -> 1339 | C14: =SUMIFS('Sales Data'!$J$2:$J$121,'Sales Data'!$B$2:$B$121,">="&A14,'Sales Data'!$B$2:$B$121,"<"&EDATE(A14,1)) -> 662 | E14: Electronics | F14: =SUMIF('Sales Data'!$D$2:$D$121,E14,'Sales Data'!$H$2:$H$121) -> 8774
A15: 45689 | B15: =SUMIFS('Sales Data'!$H$2:$H$121,'Sales Data'!$B$2:$B$121,">="&A15,'Sales Data'!$B$2:$B$121,"<"&EDATE(A15,1)) -> 1813 | C15: =SUMIFS('Sales Data'!$J$2:$J$121,'Sales Data'!$B$2:$B$121,">="&A15,'Sales Data'!$B$2:$B$121,"<"&EDATE(A15,1)) -> 791 | E15: Office Supplies | F15: =SUMIF('Sales Data'!$D$2:$D$121,E15,'Sales Data'!$H$2:$H$121) -> 4176
A16: 45717 | B16: =SUMIFS('Sales Data'!$H$2:$H$121,'Sales Data'!$B$2:$B$121,">="&A16,'Sales Data'!$B$2:$B$121,"<"&EDATE(A16,1)) -> 295 | C16: =SUMIFS('Sales Data'!$J$2:$J$121,'Sales Data'!$B$2:$B$121,">="&A16,'Sales Data'!$B$2:$B$121,"<"&EDATE(A16,1)) -> 134 | E16: Furniture | F16: =SUMIF('Sales Data'!$D$2:$D$121,E16,'Sales Data'!$H$2:$H$121) -> 12316
A17: 45748 | B17: =SUMIFS('Sales Data'!$H$2:$H$121,'Sales Data'!$B$2:$B$121,">="&A17,'Sales Data'!$B$2:$B$121,"<"&EDATE(A17,1)) -> 1107 | C17: =SUMIFS('Sales Data'!$J$2:$J$121,'Sales Data'!$B$2:$B$121,">="&A17,'Sales Data'!$B$2:$B$121,"<"&EDATE(A17,1)) -> 514
A18: 45778 | B18: =SUMIFS('Sales Data'!$H$2:$H$121,'Sales Data'!$B$2:$B$121,">="&A18,'Sales Data'!$B$2:$B$121,"<"&EDATE(A18,1)) -> 3470 | C18: =SUMIFS('Sales Data'!$J$2:$J$121,'Sales Data'!$B$2:$B$121,">="&A18,'Sales Data'!$B$2:$B$121,"<"&EDATE(A18,1)) -> 1235
A19: 45809 | B19: =SUMIFS('Sales Data'!$H$2:$H$121,'Sales Data'!$B$2:$B$121,">="&A19,'Sales Data'!$B$2:$B$121,"<"&EDATE(A19,1)) -> 1374 | C19: =SUMIFS('Sales Data'!$J$2:$J$121,'Sales Data'!$B$2:$B$121,">="&A19,'Sales Data'!$B$2:$B$121,"<"&EDATE(A19,1)) -> 632
A20: 45839 | B20: =SUMIFS('Sales Data'!$H$2:$H$121,'Sales Data'!$B$2:$B$121,">="&A20,'Sales Data'!$B$2:$B$121,"<"&EDATE(A20,1)) -> 2012 | C20: =SUMIFS('Sales Data'!$J$2:$J$121,'Sales Data'!$B$2:$B$121,">="&A20,'Sales Data'!$B$2:$B$121,"<"&EDATE(A20,1)) -> 746
A21: 45870 | B21: =SUMIFS('Sales Data'!$H$2:$H$121,'Sales Data'!$B$2:$B$121,">="&A21,'Sales Data'!$B$2:$B$121,"<"&EDATE(A21,1)) -> 2341 | C21: =SUMIFS('Sales Data'!$J$2:$J$121,'Sales Data'!$B$2:$B$121,">="&A21,'Sales Data'!$B$2:$B$121,"<"&EDATE(A21,1)) -> 948
A22: 45901 | B22: =SUMIFS('Sales Data'!$H$2:$H$121,'Sales Data'!$B$2:$B$121,">="&A22,'Sales Data'!$B$2:$B$121,"<"&EDATE(A22,1)) -> 3348 | C22: =SUMIFS('Sales Data'!$J$2:$J$121,'Sales Data'!$B$2:$B$121,">="&A22,'Sales Data'!$B$2:$B$121,"<"&EDATE(A22,1)) -> 1437
A23: 45931 | B23: =SUMIFS('Sales Data'!$H$2:$H$121,'Sales Data'!$B$2:$B$121,">="&A23,'Sales Data'!$B$2:$B$121,"<"&EDATE(A23,1)) -> 3713 | C23: =SUMIFS('Sales Data'!$J$2:$J$121,'Sales Data'!$B$2:$B$121,">="&A23,'Sales Data'!$B$2:$B$121,"<"&EDATE(A23,1)) -> 1511
A24: 45962 | B24: =SUMIFS('Sales Data'!$H$2:$H$121,'Sales Data'!$B$2:$B$121,">="&A24,'Sales Data'!$B$2:$B$121,"<"&EDATE(A24,1)) -> 2446 | C24: =SUMIFS('Sales Data'!$J$2:$J$121,'Sales Data'!$B$2:$B$121,">="&A24,'Sales Data'!$B$2:$B$121,"<"&EDATE(A24,1)) -> 1177
A25: 45992 | B25: =SUMIFS('Sales Data'!$H$2:$H$121,'Sales Data'!$B$2:$B$121,">="&A25,'Sales Data'!$B$2:$B$121,"<"&EDATE(A25,1)) -> 2008 | C25: =SUMIFS('Sales Data'!$J$2:$J$121,'Sales Data'!$B$2:$B$121,">="&A25,'Sales Data'!$B$2:$B$121,"<"&EDATE(A25,1)) -> 903

Sheet Sales Data
A1: Order ID | B1: Order Date | C1: Region | D1: Category | E1: Product | F1: Quantity | G1: Unit Price | H1: Sales | I1: Cost | J1: Profit
A2: ORD-0001 | B2: 45666 | C2: South | D2: Office Supplies | E2: Notebook Pack | F2: 3 | G2: 12 | H2: 36 | I2: 15 | J2: 21
A3: ORD-0002 | B3: 45998 | C3: East | D3: Furniture | E3: Desk Lamp | F3: 10 | G3: 38 | H3: 380 | I3: 210 | J3: 170
A4: ORD-0003 | B4: 45822 | C4: South | D4: Furniture | E4: Desk Lamp | F4: 1 | G4: 38 | H4: 38 | I4: 21 | J4: 17
A5: ORD-0004 | B5: 46020 | C5: West | D5: Office Supplies | E5: Desk Organizer | F5: 12 | G5: 20 | H5: 240 | I5: 108 | J5: 132
A6: ORD-0005 | B6: 45660 | C6: North | D6: Electronics | E6: Headphones | F6: 9 | G6: 45 | H6: 405 | I6: 243 | J6: 162
A7: ORD-0006 | B7: 45844 | C7: North | D7: Electronics | E7: Headphones | F7: 3 | G7: 45 | H7: 135 | I7: 81 | J7: 54
A8: ORD-0007 | B8: 45952 | C8: South | D8: Electronics | E8: Keyboard | F8: 12 | G8: 32 | H8: 384 | I8: 216 | J8: 168
A9: ORD-0008 | B9: 45691 | C9: West | D9: Office Supplies | E9: Notebook Pack | F9: 4 | G9: 12 | H9: 48 | I9: 20 | J9: 28
A10: ORD-0009 | B10: 45958 | C10: West | D10: Electronics | E10: Wireless Mouse | F10: 9 | G10: 18 | H10: 162 | I10: 81 | J10: 81
A11: ORD-0010 | B11: 46021 | C11: South | D11: Furniture | E11: Office Chair | F11: 3 | G11: 120 | H11: 360 | I11: 246 | J11: 114
A12: ORD-0011 | B12: 45858 | C12: South | D12: Office Supplies | E12: Printer Paper | F12: 10 | G12: 8 | H12: 80 | I12: 40 | J12: 40
A13: ORD-0012 | B13: 45784 | C13: South | D13: Office Supplies | E13: Notebook Pack | F13: 7 | G13: 12 | H13: 84 | I13: 35 | J13: 49
... A121: ORD-0120 | B121: 45926 | C121: South | D121: Furniture | E121: Desk Lamp | F121: 5 | G121: 38 | H121: 190 | I121: 105 | J121: 85
